hmmCNV/__init__.py
hmmCNV/em_utilities.py
hmmCNV/hmm/__init__.py
hmmCNV/hmm/hmm.c
hmmCNV/hmm/hmm.pyx
hmmCNV/hmm/utilities.c
hmmCNV/hmmCNV.py
hmmCNV/hmm_utilities.py
hmmcnv-1.1.7.dist-info/METADATA
hmmcnv-1.1.7.dist-info/WHEEL
hmmcnv-1.1.7.dist-info/licenses/LICENSE.md
hmmcnv-1.1.7.dist-info/RECORD
